indentlogger/__init__.py
indentlogger/indent_logger.py
indentlogger-0.1.0.dist-info/METADATA
indentlogger-0.1.0.dist-info/WHEEL
indentlogger-0.1.0.dist-info/top_level.txt
indentlogger-0.1.0.dist-info/RECORD
