Metadata-Version: 2.4
Name: indentlogger
Version: 0.1.0
Summary: An advanced indentation-based logging library for Python. Easily trace and format function calls with nested ASCII boxes or minimal pipes.
Author-email: Avi <sixfold.fellas4a@icloud.com>
License-Expression: MIT
Project-URL: Homepage, https://aviralgarg.com
Project-URL: Source, https://github.com/gaviral/indentlogger
Keywords: logging,indentation,debugging,function calls,python
Classifier: Programming Language :: Python :: 3
Classifier: Operating System :: OS Independent
Requires-Python: >=3.7
